camri/.gitignore
camri/__init__.py
camri/image/__init__.py
camri/image/_imgtool.py
camri/image/_utils.py
camri/image/deprecated.py
camri/image/handler.py
camri/image/params.py
camri/image/utils.py
camri/image/viewer.py
camri/manager/__init__.py
camri/manager/project/__init__.py
camri/manager/project/dataset.py
camri/manager/project/error.py
camri/manager/project/filter.py
camri/manager/project/helper.py
camri/manager/project/items.py
camri/manager/project/parser.py
camri/manager/project/reference.py
camri/manager/workload/__init__.py
camri/manager/workload/slurm.py
camri/prep/__init__.py
camri/prep/fmri.py
camri/prep/image.py
camri/prep/qc.py
camri/prep/rsfc.py
camri/prep/signal.py
camri-0.0.0.dev0.dist-info/METADATA
camri-0.0.0.dev0.dist-info/WHEEL
camri-0.0.0.dev0.dist-info/RECORD
